odoo/addons/sale_order_general_discount_payment_term/README.rst
odoo/addons/sale_order_general_discount_payment_term/__init__.py
odoo/addons/sale_order_general_discount_payment_term/__manifest__.py
odoo/addons/sale_order_general_discount_payment_term/i18n/it.po
odoo/addons/sale_order_general_discount_payment_term/i18n/sale_order_general_discount_payment_term.pot
odoo/addons/sale_order_general_discount_payment_term/models/__init__.py
odoo/addons/sale_order_general_discount_payment_term/models/account_payment_term.py
odoo/addons/sale_order_general_discount_payment_term/models/sale_order.py
odoo/addons/sale_order_general_discount_payment_term/readme/CONTRIBUTORS.rst
odoo/addons/sale_order_general_discount_payment_term/readme/DESCRIPTION.rst
odoo/addons/sale_order_general_discount_payment_term/readme/USAGE.rst
odoo/addons/sale_order_general_discount_payment_term/static/description/icon.png
odoo/addons/sale_order_general_discount_payment_term/static/description/index.html
odoo/addons/sale_order_general_discount_payment_term/tests/__init__.py
odoo/addons/sale_order_general_discount_payment_term/tests/test_payment_term_discount.py
odoo/addons/sale_order_general_discount_payment_term/views/account_payment_term_view.xml
odoo14_addon_sale_order_general_discount_payment_term-14.0.2.0.0.dist-info/METADATA
odoo14_addon_sale_order_general_discount_payment_term-14.0.2.0.0.dist-info/WHEEL
odoo14_addon_sale_order_general_discount_payment_term-14.0.2.0.0.dist-info/top_level.txt
odoo14_addon_sale_order_general_discount_payment_term-14.0.2.0.0.dist-info/RECORD
