Metadata-Version: 2.1
Name: odoo14-addon-sale-order-general-discount-payment-term
Version: 14.0.2.0.0
Summary: General discount per sale order set on payment term
Home-page: https://github.com/OCA/sale-workflow
Author: Nextev,Ooops,Odoo Community Association (OCA)
Author-email: support@odoo-community.org
License: AGPL-3
Platform: UNKNOWN
Classifier: Programming Language :: Python
Classifier: Framework :: Odoo
Classifier: Framework :: Odoo :: 14.0
Classifier: License :: OSI Approved :: GNU Affero General Public License v3
Requires-Python: >=3.6
Requires-Dist: odoo14-addon-sale-order-general-discount
Requires-Dist: odoo <14.1dev,>=14.0a
